HW2/OtherCanRunVersionYO/fifo.v
module fifo (data_i, write_i, read_i, full_o, empty_o, data_o, clk, rst_n);
parameter DWIDTH = 8, FDEPTH = 5;

input wire [DWIDTH-1:0] data_i;
input wire write_i, read_i;
output wire full_o, empty_o;
output reg [DWIDTH-1:0] data_o;
input wire clk, rst_n;



reg [7:0] mem [4:0];
reg [2:0] write_ptr;
reg [2:0] read_ptr;
reg [2:0] mem_ct;


assign empty_o = (mem_ct[2:0] == 0);
assign full_o = (mem_ct[2:0] == 5);

// should consider the condition of (write_i && read_i), (write_i), (read_i) 
always @(posedge clk, negedge rst_n) begin
    if (!rst_n) begin
        write_ptr <= 0;
        read_ptr <= 0;
        data_o <= 0;
        mem_ct <= 0;
        mem[0] <= 0;
        mem[1] <= 0;
        mem[2] <= 0;
        mem[3] <= 0;
        mem[4] <= 0;
    end else begin
        case ({write_i, read_i})
        2'b00: begin
            data_o <= data_o;
        end
        2'b10: begin
            mem [write_ptr] <= data_i;
            write_ptr <= (write_ptr==4)? 0 : write_ptr + 1'b1;
            mem_ct <= mem_ct + 1;
            end
        2'b01: begin
            data_o <= mem [read_ptr];
            read_ptr <= (read_ptr==4)? 0 : read_ptr + 1'b1;
            mem_ct <= mem_ct - 1;
            end
        2'b11: begin
            if (empty_o) begin
                data_o <= data_i;
            end else begin
                mem [write_ptr] <= data_i;
                data_o <= mem [read_ptr];
                write_ptr <= (write_ptr==4)? 0 : write_ptr + 1'b1;
                read_ptr <= (read_ptr==4)? 0 : read_ptr + 1'b1;
            end
        end
        endcase
    end
end

endmodule

HW2/OtherCanRunVersionYO/path.v
module path(clk, rst_n, data1_i, data2_i, valid1_i, valid2_i, data_o, req_o, gnt_i, stop1_o, stop2_o, valid_o);

parameter DWIDTH = 8;
parameter FDEPTH = 5;
input clk;
input rst_n;
input [DWIDTH-1:0] data1_i;
input [DWIDTH-1:0] data2_i;
input valid1_i;
input valid2_i;
input gnt_i;
output req_o;
output stop1_o;
output stop2_o;
output [DWIDTH-1:0] data_o;
output reg valid_o;


wire [DWIDTH-1:0] fifo_o;
wire full, empty, valid_i, almost_full;
wire bypass;
wire read_i;
wire write_i;
wire [DWIDTH-1:0] data_i;
reg sel_i; // 1'b0:turn to data1 can input, 1'b1:turn to data2 can input
reg [3:0] data_i_ct;
reg [DWIDTH-1:0] data_i_r;

assign valid_i = (valid1_i || valid2_i);
//assign req_o = (valid_i || read_i);
assign req_o = (empty == 0 || valid_i);
assign data_i = (sel_i == 0)? data1_i : data2_i;
assign bypass = (gnt_i && valid_i && empty);
assign write_i = ((full == 0) || (almost_full == 1)) && (valid_i == 1) && (bypass == 0);// consider bypass
assign read_i = (empty == 0) && (gnt_i == 1);
//assign valid_o = (gnt_i == 1);
assign data_o = (bypass == 1)? data_i_r : fifo_o;
assign almost_full = (full & read_i)? 1 : 0;
//及時送出
assign stop1_o = ((full == 1) && (read_i == 0) && (bypass == 0)) || (sel_i == 1);
assign stop2_o = ((full == 1) && (read_i == 0) && (bypass == 0)) || (sel_i == 0);
//及時送出
always@ (data_i_ct) begin
    if (data_i_ct == 10) begin
        sel_i = ~sel_i;
    end else begin
        sel_i = sel_i;
    end
end

always@(posedge clk, negedge rst_n)	begin
    if (!rst_n) begin
        data_i_ct <= 0;
        sel_i <= 0;
	end else begin
        if (bypass) begin
            data_i_r <= data_i;
            data_i_ct <= (data_i_ct == 10)? 1 : data_i_ct + 1;
        end else if (write_i) begin
            data_i_ct <= (data_i_ct == 10)? 1 : data_i_ct + 1;
        end else begin
            sel_i <= sel_i;
        end
        /*原本是再等一個clock
        stop1_o <= ((full == 1) && (read_i == 0) && (bypass == 0)) || (sel_i == 1);
        stop2_o <= ((full == 1) && (read_i == 0) && (bypass == 0)) || (sel_i == 0);
        *///原本是再等一個clock
        valid_o <= (gnt_i == 1);
    end
end

fifo fifo_inst (.data_i(data_i), .write_i(write_i), .read_i(read_i),
                .full_o(full), .empty_o(empty),
                .data_o(fifo_o), .clk(clk), .rst_n(rst_n));

endmodule

HW2/OtherTestbench/zhongMon/tb.v
`timescale 1ns/10ps
`define CYCLE      10.00         	 // Modify your clock period here
`define End_CYCLE  100000            // Modify cycle times once your design need more cycle times!
`define PAT1        "./pattern1.dat" // Master1 output data   
`define PAT2        "./pattern2.dat" // Master2 output data
`define EXP        "./golden1.dat"   // Memory stored data (ground truth), is used to verified your designed
module tb;

parameter DWIDTH = 8;
parameter FDEPTH = 5;
reg clk, rst;
reg [DWIDTH-1:0] test_data1[0:19];
reg [DWIDTH-1:0] test_data2[0:19];
reg [DWIDTH-1:0] test_mem[0:39];
integer count1;
integer count2;
reg [6:0] mem_count;
reg valid1_i, valid2_i;
wire req_o, valid_o;
reg gnt_i;
wire stop1_o, stop2_o;
reg [DWIDTH-1:0] data1_i;
reg [DWIDTH-1:0] data2_i;
wire [DWIDTH-1:0] data_o;
integer err;


path p(.clk(clk), .rst_n(rst), .data1_i(data1_i), .data2_i(data2_i), .valid1_i(valid1_i), 
        .valid2_i(valid2_i), .data_o(data_o), .req_o(req_o), .gnt_i(gnt_i), .stop1_o(stop1_o), 
        .stop2_o(stop2_o), .valid_o(valid_o));

        
always #(`CYCLE/2) begin
    clk = ~clk;
end

initial begin
    $fsdbDumpfile("tb.fsdb");
    $fsdbDumpvars(0,tb,"+mda");
    $readmemb(`PAT1, test_data1);
    $readmemb(`PAT2, test_data2);
    $readmemb(`EXP, test_mem);
    rst = 1'd1; clk = 1'd0; gnt_i = 1'd0;
    count1 = 0; count2 = 0; mem_count = 7'd0;
    err = 0;
    #5  rst = ~rst;
    #5  rst = ~rst;
    #`End_CYCLE $finish;
end



always #(({$random}%5+1)*`CYCLE) begin
    if(!stop1_o) begin
        data1_i = test_data1[count1];
        valid1_i = 1'd1;
        valid2_i = 1'd0;
        #`CYCLE valid1_i = 1'd0;
        count1 = count1+1;
    end


    
    if(!stop2_o) begin
        data2_i = test_data2[count2];
        valid2_i = 1'd1;
        valid1_i = 1'd0;
        #`CYCLE valid2_i = 1'd0;
        count2 = count2+1;
    end

end

always #(({$random}%5+1)*`CYCLE) begin
    if(req_o) begin
        gnt_i = 1'd1;
        #`CYCLE gnt_i = 1'd0;
    end
end

always @(negedge clk) begin
    if(valid_o) begin
        if(data_o!=test_mem[mem_count]) begin
            err <= err+1; 
        end
    mem_count <= mem_count+1;
    end
    if(mem_count==40) begin
        if(err==0) 
            $display("\n    Congratulations!!\n\n");
        else
            $display("\n    Code has %4d errors. \n\n",err);
        #(`CYCLE*3) $finish;
    end
end

endmodule

HW2/OtherCanRunVersionYO/tb.vcd
$date
	Tue Nov 06 21:51:56 2018
$end
$version
	Icarus Verilog
$end
$timescale
	10ps
$end
$scope module tb $end
$var wire 8 ! data_o [7:0] $end
$var wire 1 " req_o $end
$var wire 1 # stop1_o $end
$var wire 1 $ stop2_o $end
$var wire 1 % valid_o $end
$var reg 1 & clk $end
$var integer 32 ' count1 [31:0] $end
$var integer 32 ( count2 [31:0] $end
$var reg 8 ) data1_i [7:0] $end
$var reg 8 * data2_i [7:0] $end
$var integer 32 + err [31:0] $end
$var reg 1 , gnt_i $end
$var reg 7 - mem_count [6:0] $end
$var reg 1 . rst $end
$var reg 1 / valid1_i $end
$var reg 1 0 valid2_i $end
$scope module p $end
$var wire 1 1 almost_full $end
$var wire 1 2 bypass $end
$var wire 1 3 clk $end
$var wire 8 4 data1_i [7:0] $end
$var wire 8 5 data2_i [7:0] $end
$var wire 8 6 data_i [7:0] $end
$var wire 8 7 data_o [7:0] $end
$var wire 1 8 empty $end
$var wire 8 9 fifo_o [7:0] $end
$var wire 1 : full $end
$var wire 1 ; gnt_i $end
$var wire 1 < read_i $end
$var wire 1 " req_o $end
$var wire 1 = rst_n $end
$var wire 1 # stop1_o $end
$var wire 1 $ stop2_o $end
$var wire 1 > valid1_i $end
$var wire 1 ? valid2_i $end
$var wire 1 @ valid_i $end
$var wire 1 A write_i $end
$var reg 4 B data_i_ct [3:0] $end
$var reg 8 C data_i_r [7:0] $end
$var reg 1 D sel_i $end
$var reg 1 E valid_o $end
$scope module fifo_inst $end
$var wire 1 3 clk $end
$var wire 8 F data_i [7:0] $end
$var wire 1 8 empty_o $end
$var wire 1 : full_o $end
$var wire 1 < read_i $end
$var wire 1 = rst_n $end
$var wire 1 A write_i $end
$var reg 8 G data_o [7:0] $end
$var reg 3 H mem_ct [2:0] $end
$var reg 3 I read_ptr [2:0] $end
$var reg 3 J write_ptr [2:0] $end
$upscope $end
$upscope $end
$upscope $end
$enddefinitions $end
#0
$dumpvars
bx J
bx I
bx H
bx G
bx F
xE
xD
bx C
bx B
xA
x@
x?
x>
1=
0<
0;
x:
bx 9
x8
bx 7
bx 6
bx 5
bx 4
03
02
01
x0
x/
1.
b0 -
0,
b0 +
bx *
bx )
b0 (
b0 '
0&
x%
x$
x#
x"
bx !
$end
#500
0#
b0 !
b0 7
1$
b0 H
18
0:
b0 G
b0 9
b0 I
b0 J
0D
b0 B
0.
0=
1&
13
#1000
1.
1=
0&
03
#1500
0E
0%
1&
13
#2000
0&
03
#2500
1&
13
#3000
0&
03
#3500
1&
13
#4000
1A
1"
1@
b0 6
b0 F
0&
03
00
0?
1/
1>
b0 )
b0 4
#4500
b1 H
08
b1 J
b1 B
1&
13
#5000
0A
0@
0&
03
b1 '
0/
0>
#5500
1&
13
#6000
1<
0&
03
1,
1;
#6500
0<
0"
b0 H
18
b1 I
1E
1%
1&
13
#7000
b1 -
0&
03
0,
0;
#7500
0E
0%
1&
13
#8000
1A
1"
1@
b1 6
b1 F
0&
03
1/
1>
b1 )
b1 4
#8500
b1 H
08
b10 J
b10 B
1&
13
#9000
0A
0@
0&
03
b10 '
0/
0>
#9500
1&
13
#10000
1<
0&
03
1,
1;
#10500
0<
0"
b1 !
b1 7
b0 H
18
b10 I
b1 G
b1 9
1E
1%
1&
13
#11000
b10 -
0&
03
0,
0;
#11500
0E
0%
1&
13
#12000
1A
1"
1@
b10 6
b10 F
0&
03
1/
1>
b10 )
b10 4
#12500
b1 H
08
b11 J
b11 B
1&
13
#13000
0A
0@
0&
03
b11 '
0/
0>
#13500
1&
13
#14000
0&
03
#14500
1&
13
#15000
1A
1@
b11 6
b11 F
1<
0&
03
1/
1>
b11 )
b11 4
1,
1;
#15500
b10 !
b10 7
1E
1%
b100 B
b11 I
b100 J
b10 G
b10 9
1&
13
#16000
b11 -
0A
0@
0<
0&
03
b100 '
0/
0>
0,
0;
#16500
0E
0%
1&
13
#17000
0&
03
#17500
1&
13
#18000
0&
03
#18500
1&
13
#19000
0&
03
#19500
1&
13
#20000
1A
1@
b100 6
b100 F
0&
03
1/
1>
b100 )
b100 4
#20500
b10 H
b0 J
b101 B
1&
13
#21000
0A
0@
1<
0&
03
b101 '
0/
0>
1,
1;
#21500
b11 !
b11 7
1E
1%
b1 H
b100 I
b11 G
b11 9
1&
13
#22000
b100 -
0<
0&
03
0,
0;
#22500
0E
0%
1&
13
#23000
0&
03
#23500
1&
13
#24000
1A
1@
b101 6
b101 F
0&
03
1/
1>
b101 )
b101 4
#24500
b10 H
b1 J
b110 B
1&
13
#25000
0A
0@
0&
03
b110 '
0/
0>
#25500
1&
13
#26000
0&
03
#26500
1&
13
#27000
1<
0&
03
1,
1;
#27500
b100 !
b100 7
1E
1%
b1 H
b0 I
b100 G
b100 9
1&
13
#28000
b101 -
1A
0<
1@
b110 6
b110 F
0&
03
0,
0;
1/
1>
b110 )
b110 4
#28500
b10 H
b10 J
0E
0%
b111 B
1&
13
#29000
0A
0@
0&
03
b111 '
0/
0>
#29500
1&
13
#30000
0&
03
#30500
1&
13
#31000
1A
1@
b111 6
b111 F
0&
03
1/
1>
b111 )
b111 4
#31500
b1000 B
b11 H
b11 J
1&
13
#32000
0A
0@
0&
03
b1000 '
0/
0>
#32500
1&
13
#33000
1<
0&
03
1,
1;
#33500
b101 !
b101 7
1E
1%
b10 H
b1 I
b101 G
b101 9
1&
13
#34000
b110 -
0<
0&
03
0,
0;
#34500
0E
0%
1&
13
#35000
1A
1@
b1000 6
b1000 F
0&
03
1/
1>
b1000 )
b1000 4
#35500
b1001 B
b11 H
b100 J
1&
13
#36000
0A
0@
0&
03
b1001 '
0/
0>
#36500
1&
13
#37000
1A
1@
b1001 6
b1001 F
1<
0&
03
1/
1>
b1001 )
b1001 4
1,
1;
#37500
bx 6
bx F
1#
0$
1D
b110 !
b110 7
1E
1%
b1010 B
b10 I
b0 J
b110 G
b110 9
1&
13
#38000
b111 -
b1010 6
b1010 F
0<
0&
03
10
1?
b1010 *
b1010 5
b1010 '
0/
0>
0,
0;
#38500
b100 H
b1 J
0E
0%
b1 B
1&
13
#39000
0A
0@
1<
0&
03
b1 (
00
0?
1,
1;
#39500
b111 !
b111 7
1E
1%
b11 H
b11 I
b111 G
b111 9
1&
13
#40000
b1000 -
0<
0&
03
0,
0;
#40500
0E
0%
1&
13
#41000
0&
03
#41500
1&
13
#42000
0&
03
#42500
1&
13
#43000
0&
03
#43500
1&
13
#44000
1A
1@
b1011 6
b1011 F
0&
03
10
1?
b1011 *
b1011 5
#44500
b100 H
b10 J
b10 B
1&
13
#45000
0A
0@
1<
0&
03
b10 (
00
0?
1,
1;
#45500
b1000 !
b1000 7
1E
1%
b11 H
b100 I
b1000 G
b1000 9
1&
13
#46000
b1001 -
0<
0&
03
0,
0;
#46500
0E
0%
1&
13
#47000
1A
1<
1@
b1100 6
b1100 F
0&
03
1,
1;
10
1?
b1100 *
b1100 5
#47500
b1001 !
b1001 7
1E
1%
b11 B
b0 I
b11 J
b1001 G
b1001 9
1&
13
#48000
b1010 -
0A
0<
0@
0&
03
0,
0;
b11 (
00
0?
#48500
0E
0%
1&
13
#49000
0&
03
#49500
1&
13
#50000
0&
03
#50500
1&
13
#51000
0&
03
#51500
1&
13
#52000
1A
1<
1@
b1101 6
b1101 F
0&
03
1,
1;
10
1?
b1101 *
b1101 5
#52500
b1010 !
b1010 7
b1 I
b100 J
b1010 G
b1010 9
1E
1%
b100 B
1&
13
#53000
b1011 -
0A
0<
0@
0&
03
0,
0;
b100 (
00
0?
#53500
0E
0%
1&
13
#54000
0&
03
#54500
1&
13
#55000
0&
03
#55500
1&
13
#56000
0&
03
#56500
1&
13
#57000
1<
0&
03
1,
1;
#57500
b1011 !
b1011 7
1E
1%
b10 H
b10 I
b1011 G
b1011 9
1&
13
#58000
b1100 -
1A
0<
1@
b1110 6
b1110 F
0&
03
0,
0;
10
1?
b1110 *
b1110 5
#58500
b11 H
b0 J
0E
0%
b101 B
1&
13
#59000
0A
0@
0&
03
b101 (
00
0?
#59500
1&
13
#60000
0&
03
#60500
1&
13
#61000
0&
03
#61500
1&
13
#62000
0&
03
#62500
1&
13
#63000
1<
0&
03
1,
1;
#63500
b1100 !
b1100 7
1E
1%
b10 H
b11 I
b1100 G
b1100 9
1&
13
#64000
b1101 -
1A
0<
1@
b1111 6
b1111 F
0&
03
0,
0;
10
1?
b1111 *
b1111 5
#64500
b11 H
b1 J
0E
0%
b110 B
1&
13
#65000
0A
0@
0&
03
b110 (
00
0?
#65500
1&
13
#66000
1A
1@
b10000 6
b10000 F
0&
03
10
1?
b10000 *
b10000 5
#66500
b100 H
b10 J
b111 B
1&
13
#67000
0A
0@
0&
03
b111 (
00
0?
#67500
1&
13
#68000
1<
0&
03
1,
1;
#68500
b1101 !
b1101 7
b11 H
b100 I
b1101 G
b1101 9
1E
1%
1&
13
#69000
b1110 -
0<
0&
03
0,
0;
#69500
0E
0%
1&
13
#70000
0&
03
#70500
1&
13
#71000
1A
1<
1@
b10001 6
b10001 F
0&
03
1,
1;
10
1?
b10001 *
b10001 5
#71500
b1110 !
b1110 7
1E
1%
b1000 B
b0 I
b11 J
b1110 G
b1110 9
1&
13
#72000
b1111 -
0A
0<
0@
0&
03
0,
0;
b1000 (
00
0?
#72500
0E
0%
1&
13
#73000
0&
03
#73500
1&
13
#74000
1<
0&
03
1,
1;
#74500
b1111 !
b1111 7
b10 H
b1 I
b1111 G
b1111 9
1E
1%
1&
13
#75000
b10000 -
0<
0&
03
0,
0;
#75500
0E
0%
1&
13
#76000
0&
03
#76500
1&
13
#77000
1A
1@
b10010 6
b10010 F
0&
03
10
1?
b10010 *
b10010 5
#77500
b1001 B
b11 H
b100 J
1&
13
#78000
0A
0@
1<
0&
03
b1001 (
00
0?
1,
1;
#78500
b10000 !
b10000 7
b10 H
b10 I
b10000 G
b10000 9
1E
1%
1&
13
#79000
b10001 -
0<
0&
03
0,
0;
#79500
0E
0%
1&
13
#80000
1A
1@
b10011 6
b10011 F
0&
03
10
1?
b10011 *
b10011 5
#80500
b1001 6
b1001 F
0#
1$
0D
b11 H
b0 J
b1010 B
1&
13
#81000
0A
0@
1<
0&
03
b1010 (
00
0?
1,
1;
#81500
b10001 !
b10001 7
1E
1%
b10 H
b11 I
b10001 G
b10001 9
1&
13
#82000
b10010 -
0<
0&
03
0,
0;
#82500
0E
0%
1&
13
#83000
1<
0&
03
1,
1;
#83500
b10010 !
b10010 7
1E
1%
b1 H
b100 I
b10010 G
b10010 9
1&
13
#84000
b10011 -
0<
0&
03
0,
0;
#84500
0E
0%
1&
13
#85000
1A
1<
1@
b10100 6
b10100 F
0&
03
1,
1;
1/
1>
b10100 )
b10100 4
#85500
b10011 !
b10011 7
1E
1%
b1 B
b0 I
b1 J
b10011 G
b10011 9
1&
13
#86000
b10100 -
0A
0<
0@
0&
03
0,
0;
b1011 '
0/
0>
#86500
0E
0%
1&
13
#87000
0&
03
#87500
1&
13
#88000
0&
03
#88500
1&
13
#89000
1<
0&
03
1,
1;
#89500
0<
0"
b10100 !
b10100 7
1E
1%
b0 H
18
b1 I
b10100 G
b10100 9
1&
13
#90000
b10101 -
1A
1"
1@
b10101 6
b10101 F
0&
03
0,
0;
1/
1>
b10101 )
b10101 4
#90500
b1 H
08
b10 J
0E
0%
b10 B
1&
13
#91000
0A
0@
0&
03
b1100 '
0/
0>
#91500
1&
13
#92000
1<
0&
03
1,
1;
#92500
0<
0"
b10101 !
b10101 7
b0 H
18
b10 I
b10101 G
b10101 9
1E
1%
1&
13
#93000
b10110 -
0&
03
0,
0;
#93500
0E
0%
1&
13
#94000
0&
03
#94500
1&
13
#95000
0&
03
#95500
1&
13
#96000
1A
1"
1@
b10110 6
b10110 F
0&
03
1/
1>
b10110 )
b10110 4
#96500
b1 H
08
b11 J
b11 B
1&
13
#97000
0A
1<
0@
0&
03
1,
1;
b1101 '
0/
0>
#97500
0<
0"
b10110 !
b10110 7
1E
1%
b0 H
18
b11 I
b10110 G
b10110 9
1&
13
#98000
b10111 -
0&
03
0,
0;
#98500
0E
0%
1&
13
#99000
1A
1"
1@
b10111 6
b10111 F
0&
03
1/
1>
b10111 )
b10111 4
#99500
b100 B
b1 H
08
b100 J
1&
13
#100000
0A
0@
0&
03
b1110 '
0/
0>
#100500
1&
13
#101000
0&
03
#101500
1&
13
#102000
1A
1@
b11000 6
b11000 F
1<
0&
03
1/
1>
b11000 )
b11000 4
1,
1;
#102500
b10111 !
b10111 7
b100 I
b0 J
b10111 G
b10111 9
1E
1%
b101 B
1&
13
#103000
b11000 -
0A
0@
0<
0&
03
b1111 '
0/
0>
0,
0;
#103500
0E
0%
1&
13
#104000
1<
0&
03
1,
1;
#104500
0<
0"
b11000 !
b11000 7
b0 H
18
b0 I
b11000 G
b11000 9
1E
1%
1&
13
#105000
b11001 -
0&
03
0,
0;
#105500
0E
0%
1&
13
#106000
1A
1"
1@
b11001 6
b11001 F
0&
03
1/
1>
b11001 )
b11001 4
#106500
b1 H
08
b1 J
b110 B
1&
13
#107000
0A
0@
0&
03
b10000 '
0/
0>
#107500
1&
13
#108000
1A
1@
b11010 6
b11010 F
0&
03
1/
1>
b11010 )
b11010 4
#108500
b10 H
b10 J
b111 B
1&
13
#109000
0A
0@
0&
03
b10001 '
0/
0>
#109500
1&
13
#110000
1<
0&
03
1,
1;
#110500
b11001 !
b11001 7
b1 H
b1 I
b11001 G
b11001 9
1E
1%
1&
13
#111000
b11010 -
0<
0&
03
0,
0;
#111500
0E
0%
1&
13
#112000
0&
03
#112500
1&
13
#113000
0&
03
#113500
1&
13
#114000
1A
1<
1@
b11011 6
b11011 F
0&
03
1,
1;
1/
1>
b11011 )
b11011 4
#114500
b11010 !
b11010 7
b10 I
b11 J
b11010 G
b11010 9
1E
1%
b1000 B
1&
13
#115000
b11011 -
0A
0<
0@
0&
03
0,
0;
b10010 '
0/
0>
#115500
0E
0%
1&
13
#116000
0&
03
#116500
1&
13
#117000
1A
1<
1@
b11100 6
b11100 F
0&
03
1,
1;
1/
1>
b11100 )
b11100 4
#117500
b11011 !
b11011 7
1E
1%
b1001 B
b11 I
b100 J
b11011 G
b11011 9
1&
13
#118000
b11100 -
0A
0<
0@
0&
03
0,
0;
b10011 '
0/
0>
#118500
0E
0%
1&
13
#119000
0&
03
#119500
1&
13
#120000
1A
1@
b11101 6
b11101 F
0&
03
1/
1>
b11101 )
b11101 4
#120500
b10011 6
b10011 F
1#
0$
1D
b10 H
b0 J
b1010 B
1&
13
#121000
b11110 6
b11110 F
0&
03
10
1?
b11110 *
b11110 5
b10100 '
0/
0>
#121500
b1 B
b11 H
b1 J
1&
13
#122000
0A
0@
0&
03
b1011 (
00
0?
#122500
1&
13
#123000
1<
0&
03
1,
1;
#123500
b11100 !
b11100 7
1E
1%
b10 H
b100 I
b11100 G
b11100 9
1&
13
#124000
b11101 -
0<
0&
03
0,
0;
#124500
0E
0%
1&
13
#125000
0&
03
#125500
1&
13
#126000
0&
03
#126500
1&
13
#127000
1A
1@
b11111 6
b11111 F
0&
03
10
1?
b11111 *
b11111 5
#127500
b10 B
b11 H
b10 J
1&
13
#128000
0A
0@
1<
0&
03
b1100 (
00
0?
1,
1;
#128500
b11101 !
b11101 7
b10 H
b0 I
b11101 G
b11101 9
1E
1%
1&
13
#129000
b11110 -
0<
0&
03
0,
0;
#129500
0E
0%
1&
13
#130000
0&
03
#130500
1&
13
#131000
1<
0&
03
1,
1;
#131500
b11110 !
b11110 7
1E
1%
b1 H
b1 I
b11110 G
b11110 9
1&
13
#132000
b11111 -
1A
0<
1@
b100000 6
b100000 F
0&
03
0,
0;
10
1?
b100000 *
b100000 5
#132500
b10 H
b11 J
0E
0%
b11 B
1&
13
#133000
0A
1<
0@
0&
03
1,
1;
b1101 (
00
0?
#133500
b11111 !
b11111 7
1E
1%
b1 H
b10 I
b11111 G
b11111 9
1&
13
#134000
b100000 -
0<
0&
03
0,
0;
#134500
0E
0%
1&
13
#135000
1A
1@
b100001 6
b100001 F
0&
03
10
1?
b100001 *
b100001 5
#135500
b100 B
b10 H
b100 J
1&
13
#136000
0A
0@
0&
03
b1110 (
00
0?
#136500
1&
13
#137000
0&
03
#137500
1&
13
#138000
0&
03
#138500
1&
13
#139000
1A
1@
b100010 6
b100010 F
1<
0&
03
10
1?
b100010 *
b100010 5
1,
1;
#139500
b100000 !
b100000 7
1E
1%
b101 B
b11 I
b0 J
b100000 G
b100000 9
1&
13
#140000
b100001 -
0A
0@
0<
0&
03
b1111 (
00
0?
0,
0;
#140500
0E
0%
1&
13
#141000
0&
03
#141500
1&
13
#142000
1<
0&
03
1,
1;
#142500
b100001 !
b100001 7
b1 H
b100 I
b100001 G
b100001 9
1E
1%
1&
13
#143000
b100010 -
0<
0&
03
0,
0;
#143500
0E
0%
1&
13
#144000
1A
1@
b100011 6
b100011 F
0&
03
10
1?
b100011 *
b100011 5
#144500
b10 H
b1 J
b110 B
1&
13
#145000
0A
0@
1<
0&
03
b10000 (
00
0?
1,
1;
#145500
b100010 !
b100010 7
1E
1%
b1 H
b0 I
b100010 G
b100010 9
1&
13
#146000
b100011 -
0<
0&
03
0,
0;
#146500
0E
0%
1&
13
#147000
0&
03
#147500
1&
13
#148000
0&
03
#148500
1&
13
#149000
0&
03
#149500
1&
13
#150000
1A
1<
1@
b100100 6
b100100 F
0&
03
1,
1;
10
1?
b100100 *
b100100 5
#150500
b100011 !
b100011 7
b1 I
b10 J
b100011 G
b100011 9
1E
1%
b111 B
1&
13
#151000
b100100 -
0A
0<
0@
0&
03
0,
0;
b10001 (
00
0?
#151500
0E
0%
1&
13
#152000
1<
0&
03
1,
1;
#152500
0<
0"
b100100 !
b100100 7
b0 H
18
b10 I
b100100 G
b100100 9
1E
1%
1&
13
#153000
b100101 -
0&
03
0,
0;
#153500
0E
0%
1&
13
#154000
0&
03
#154500
1&
13
#155000
0&
03
#155500
1&
13
#156000
1A
1"
1@
b100101 6
b100101 F
0&
03
10
1?
b100101 *
b100101 5
#156500
b1 H
08
b11 J
b1000 B
1&
13
#157000
0A
0@
0&
03
b10010 (
00
0?
#157500
1&
13
#158000
1<
0&
03
1,
1;
#158500
0<
0"
b100101 !
b100101 7
b0 H
18
b11 I
b100101 G
b100101 9
1E
1%
1&
13
#159000
b100110 -
0&
03
0,
0;
#159500
0E
0%
1&
13
#160000
0&
03
#160500
1&
13
#161000
1A
1"
1@
b100110 6
b100110 F
0&
03
10
1?
b100110 *
b100110 5
#161500
b1001 B
b1 H
08
b100 J
1&
13
#162000
0A
0@
0&
03
b10011 (
00
0?
#162500
1&
13
#163000
0&
03
#163500
1&
13
#164000
1<
0&
03
1,
1;
#164500
0<
0"
b100110 !
b100110 7
b0 H
18
b100 I
b100110 G
b100110 9
1E
1%
1&
13
#165000
b100111 -
0&
03
0,
0;
#165500
0E
0%
1&
13
#166000
0&
03
#166500
1&
13
#167000
1A
1"
1@
b100111 6
b100111 F
0&
03
10
1?
b100111 *
b100111 5
#167500
b11101 6
b11101 F
0#
1$
0D
b1010 B
b1 H
08
b0 J
1&
13
#168000
0A
0@
1<
0&
03
b10100 (
00
0?
1,
1;
#168500
0<
0"
b100111 !
b100111 7
b0 H
18
b0 I
b100111 G
b100111 9
1E
1%
1&
13
#169000
b101000 -
0&
03
0,
0;
#169500
0E
0%
1&
13
#170000
1A
1"
1@
bx 6
bx F
0&
03
1/
1>
bx )
bx 4
#170500
b1 H
08
b1 J
b1 B
1&
13
#171000
0A
0@
0&
03
b10101 '
0/
0>
#171500
1&
13
#172000
1<
0&
03
1,
1;
#172500
0<
0"
bx !
bx 7
b0 H
18
b1 I
bx G
bx 9
1E
1%
1&
13
#173000
1A
1"
1@
0&
03
0,
0;
1/
1>
